dzee_helper.py
autodzee-2.9.data/scripts/autodzee
deezer/__init__.py
deezer/utils.py
mega/__init__.py
autodzee-2.9.dist-info/LICENSE
autodzee-2.9.dist-info/METADATA
autodzee-2.9.dist-info/WHEEL
autodzee-2.9.dist-info/top_level.txt
autodzee-2.9.dist-info/RECORD
