Metadata-Version: 2.1
Name: autodzee
Version: 2.9
Summary: A Des of AutoDzee
Home-page: https://github.com/vtandroid/dokr
Author: Thanh Hoa
Author-email: getmoneykhmt3@gmail.com
License: UNKNOWN
Platform: UNKNOWN
Classifier: Programming Language :: Python :: 3
Classifier: License :: OSI Approved :: MIT License
Classifier: Operating System :: OS Independent
Requires-Dist: requests
Requires-Dist: click
Requires-Dist: pycrypto
